sphinxawesome_theme/__init__.py
sphinxawesome_theme/breadcrumbs.html
sphinxawesome_theme/builder.py
sphinxawesome_theme/code.py
sphinxawesome_theme/deprecated.py
sphinxawesome_theme/footer.html
sphinxawesome_theme/genindex.html
sphinxawesome_theme/header.html
sphinxawesome_theme/highlighting.py
sphinxawesome_theme/jinja_functions.py
sphinxawesome_theme/jsonimpl.py
sphinxawesome_theme/layout.html
sphinxawesome_theme/logos.py
sphinxawesome_theme/page.html
sphinxawesome_theme/postprocess.py
sphinxawesome_theme/prev_next.html
sphinxawesome_theme/scrolltop.html
sphinxawesome_theme/search.html
sphinxawesome_theme/searchbox.html
sphinxawesome_theme/sidebar.html
sphinxawesome_theme/sidebar_main_nav_links.html
sphinxawesome_theme/sidebar_toc.html
sphinxawesome_theme/static/0fc70aa4dfe4d16d7073.woff
sphinxawesome_theme/static/583e3f428bf2362b546d.woff
sphinxawesome_theme/static/5be6ec379613f10aea3f.woff
sphinxawesome_theme/static/76c1862325ea6f70eeff.woff2
sphinxawesome_theme/static/83710c128240451d95af.woff
sphinxawesome_theme/static/a63d39a1c104a2b3e87e.woff2
sphinxawesome_theme/static/awesome-docsearch.css
sphinxawesome_theme/static/awesome-docsearch.js
sphinxawesome_theme/static/awesome-sphinx-design.css
sphinxawesome_theme/static/awesome-sphinx-design.js
sphinxawesome_theme/static/b659956119f91f2342bc.woff2
sphinxawesome_theme/static/bb50084be2b43ba7b98c.woff2
sphinxawesome_theme/static/ce1e40901d7a0d88d483.woff2
sphinxawesome_theme/static/d04352f240062b100fba.woff2
sphinxawesome_theme/static/f1cdf5c21de970ee0592.woff
sphinxawesome_theme/static/fd994e8d90d9cab651b0.woff
sphinxawesome_theme/static/theme.css
sphinxawesome_theme/static/theme.js
sphinxawesome_theme/static/theme.js.LICENSE.txt
sphinxawesome_theme/theme.conf
sphinxawesome_theme/toc.html
sphinxawesome_theme/toc.py
sphinxawesome_theme-5.3.2.dist-info/LICENSE
sphinxawesome_theme-5.3.2.dist-info/METADATA
sphinxawesome_theme-5.3.2.dist-info/WHEEL
sphinxawesome_theme-5.3.2.dist-info/entry_points.txt
sphinxawesome_theme-5.3.2.dist-info/RECORD
