Metadata-Version: 2.1
Name: sphinxawesome-theme
Version: 5.3.2
Summary: An awesome theme for the Sphinx documentation generator
Home-page: https://sphinxawesome.xyz
License: MIT
Author: Kai Welke
Author-email: kai687@pm.me
Requires-Python: >=3.8,<4.0
Classifier: Framework :: Sphinx
Classifier: Framework :: Sphinx :: Theme
Classifier: License :: OSI Approved :: MIT License
Classifier: Programming Language :: Python
Classifier: Programming Language :: Python :: 3
Classifier: Programming Language :: Python :: 3.8
Classifier: Programming Language :: Python :: 3.9
Classifier: Programming Language :: Python :: 3.10
Classifier: Programming Language :: Python :: 3.11
Classifier: Programming Language :: Python :: 3.12
Classifier: Programming Language :: Python :: 3.13
Classifier: Topic :: Documentation
Classifier: Topic :: Documentation :: Sphinx
Classifier: Topic :: Software Development :: Documentation
Requires-Dist: beautifulsoup4 (>=4.9.1,<5.0.0)
Requires-Dist: sphinx (<7.2) ; python_version >= "3.8" and python_version < "3.9"
Requires-Dist: sphinx (>=7.2,<7.5) ; python_version >= "3.9" and python_version < "3.10"
Requires-Dist: sphinx (>=8,<9) ; python_version >= "3.10" and python_version < "3.13"
Project-URL: Documentation, https://sphinxawesome.xyz
Project-URL: Repository, https://github.com/kai687/sphinxawesome-theme
